MANIFEST.in
setup.py
Rivets.egg-info/PKG-INFO
Rivets.egg-info/SOURCES.txt
Rivets.egg-info/dependency_links.txt
Rivets.egg-info/requires.txt
Rivets.egg-info/top_level.txt
rivets/__init__.py
rivets/base.py
rivets/context.py
rivets/environment.py
rivets/errors.py
rivets/extensions.py
rivets/index.py
rivets/manifest.py
rivets/paths.py
rivets/server.py
rivets/utils.py
rivets/version.py
rivets/assets/__init__.py
rivets/assets/asset.py
rivets/assets/asset_attributes.py
rivets/assets/bundled_asset.py
rivets/assets/processed_asset.py
rivets/assets/static_asset.py
rivets/caching/__init__.py
rivets/caching/file_store.py
rivets/engines/__init__.py
rivets/engines/registry.py
rivets/mime/__init__.py
rivets/mime/registry.py
rivets/processing/__init__.py
rivets/processing/charset_normalizer.py
rivets/processing/cssmin_compressor.py
rivets/processing/directive_processor.py
rivets/processing/processor.py
rivets/processing/registry.py
rivets/processing/rjsmin_compressor.py
rivets/processing/safety_colons.py
rivets/processing/slimit_compressor.py
rivets/processing/slimmer_compressors.py
rivets/processing/uglipyjs_compressor.py
test/test_asset.py
test/test_asset_attributes.py
test/test_caching.py
test/test_context.py
test/test_directive_processor.py
test/test_engines.py
test/test_environment.py
test/test_manifest.py
test/test_performance.py
test/test_scss.py
test/test_server.py