Metadata-Version: 1.1
Name: Rivets
Version: 0.4.1
Summary: Python asset packaging system. Based on Sprockets ruby gem
Home-page: https://github.com/OiNutter/rivets
Author: Will McKenzie
Author-email: will@oinutter.co.uk
License: MIT License
Download-URL: https://github.com/OiNutter/rivets/tarball/master
Platform: UNKNOWN
Classifier: Development Status :: 3 - Alpha
Classifier: Environment :: Web Environment
Classifier: Intended Audience :: Developers
Classifier: License :: OSI Approved :: MIT License
Classifier: Programming Language :: Python :: 2
Classifier: Programming Language :: Python :: 2.6
Classifier: Programming Language :: Python :: 2.7
Classifier: Programming Language :: JavaScript
